{
  "parent": "minecraft:recipes/root",
  "rewards": {
    "recipes": [
      "minecraft:spruce_wood"
    ]
  },
  "criteria": {
    "has_log": {
      "trigger": "minecraft:impossible",
      "conditions": {
        "items": [
          {
            "item": "minecraft:spruce_log"
          }
        ]
      }
    },
    "has_the_recipe": {
      "trigger": "minecraft:impossible",
      "conditions": {
        "recipe": "minecraft:spruce_wood"
      }
    }
  },
  "requirements": [
    [
      "has_log",
      "has_the_recipe"
    ]
  ]
}